reflex_enterprise/__init__.py
reflex_enterprise/__init__.pyi
reflex_enterprise/app.py
reflex_enterprise/config.py
reflex_enterprise/constants.py
reflex_enterprise/environment.py
reflex_enterprise/proxy.py
reflex_enterprise/utils.py
reflex_enterprise/vars.py
reflex_enterprise/auth/__init__.py
reflex_enterprise/auth/cookie.py
reflex_enterprise/auth/oidc/__init__.py
reflex_enterprise/auth/oidc/config.py
reflex_enterprise/auth/oidc/state.py
reflex_enterprise/auth/oidc/types.py
reflex_enterprise/auth/oidc/utils.py
reflex_enterprise/components/__init__.py
reflex_enterprise/components/__init__.pyi
reflex_enterprise/components/component.py
reflex_enterprise/components/ag_charts/__init__.py
reflex_enterprise/components/ag_charts/base.py
reflex_enterprise/components/ag_charts/base.pyi
reflex_enterprise/components/ag_grid/__init__.py
reflex_enterprise/components/ag_grid/aggrid.py
reflex_enterprise/components/ag_grid/aggrid.pyi
reflex_enterprise/components/ag_grid/constants.py
reflex_enterprise/components/ag_grid/datasource.py
reflex_enterprise/components/ag_grid/handlers.py
reflex_enterprise/components/ag_grid/handlers.pyi
reflex_enterprise/components/ag_grid/resource.py
reflex_enterprise/components/ag_grid/resource.pyi
reflex_enterprise/components/ag_grid/utils.py
reflex_enterprise/components/ag_grid/wrapper.py
reflex_enterprise/components/ag_grid/resources/__init__.py
reflex_enterprise/components/ag_grid/resources/base.py
reflex_enterprise/components/ag_grid/resources/column.py
reflex_enterprise/components/ag_grid/resources/params.py
reflex_enterprise/components/dnd/__init__.py
reflex_enterprise/components/dnd/dnd.py
reflex_enterprise/components/dnd/dnd.pyi
reflex_enterprise/components/flow/__init__.py
reflex_enterprise/components/flow/flow.py
reflex_enterprise/components/flow/flow.pyi
reflex_enterprise/components/flow/hooks.py
reflex_enterprise/components/flow/types.py
reflex_enterprise/components/flow/util.py
reflex_enterprise/components/mantine/__init__.py
reflex_enterprise-0.4.2.dist-info/METADATA
reflex_enterprise-0.4.2.dist-info/WHEEL
reflex_enterprise-0.4.2.dist-info/licenses/LICENSE
reflex_enterprise-0.4.2.dist-info/RECORD
