Metadata-Version: 2.4
Name: reflex-enterprise
Version: 0.4.2
Summary: Package containing the paid features for Reflex. [Pro/Team/Enterprise]
Project-URL: homepage, https://reflex.dev/
Project-URL: documentation, https://enterprise.reflex.dev
Author-email: Nikhil Rao <nikhil@reflex.dev>, Alek Petuskey <alek@reflex.dev>, Masen Furer <masen@reflex.dev>, Thomas Brandého <thomas@reflex.dev>
License-Expression: LicenseRef-Proprietary
License-File: LICENSE
Keywords: python,reflex,reflex-enterprise
Requires-Python: <4.0,>=3.10
Requires-Dist: asgiproxy>=0.2.0
Requires-Dist: httpx
Requires-Dist: joserfc
Requires-Dist: psutil
Requires-Dist: reflex>=0.8.0
